llm_context_packer/__init__.py
llm_context_packer/core.py
llm_context_packer/ignore.py
llm_context_packer/main.py
llm_context_packer/utils.py
llm_context_packer-0.1.1.dist-info/licenses/LICENSE
llm_context_packer-0.1.1.dist-info/METADATA
llm_context_packer-0.1.1.dist-info/WHEEL
llm_context_packer-0.1.1.dist-info/entry_points.txt
llm_context_packer-0.1.1.dist-info/top_level.txt
llm_context_packer-0.1.1.dist-info/RECORD
