Metadata-Version: 2.4
Name: llm-context-packer
Version: 0.1.1
Summary: Turn your entire codebase into a single prompt-ready text file.
Author: Wael SAHLI
Classifier: Programming Language :: Python :: 3
Classifier: License :: OSI Approved :: MIT License
Classifier: Operating System :: OS Independent
Requires-Python: >=3.9
License-File: LICENSE
Requires-Dist: typer[all]>=0.9.0
Requires-Dist: tiktoken>=0.5.0
Requires-Dist: pathspec>=0.11.0
Requires-Dist: pyperclip>=1.8.2
Dynamic: license-file
